Workbook

Sheet Protheus
A1: CODIGO | B1: DENOMINACION | C1: TD | D1: Nº DOCUMENTO | E1: IVA | F1: FECHA | G1: ESP | H1: SERIE | I1: NUMERO | J1: % IVA | K1: TOTAL | L1: GRAVADO | M1: EXEN/NO GRAV | N1: IVA | O1: IVA Percep | P1: IIBB Percep | Q1: OTROS | R1: EXCL.NET.GRAV | S1: Unido | T1: AFIP IVA | U1: Cmparacion IVA | V1: AFIP Total | W1: Cmparacion Total
A2: 000967 | B2: ZEOCAR SACI | C2: 80 | D2: 30562597464 | E2: I | F2: 22/09/2025 | G2: NCP | H2: A1 | I2: 000400025904 | J2: 21 | K2: -459949.14 | L2: -380123.26 | M2: 0 | N2: -79825.88 | O2: 0 | P2: 0 | Q2: 0 | R2: 0 | S2: =D2&I2 -> 30562597464000400025904 | T2: =IFERROR(VLOOKUP(S2,AFIP!$F$2:$R$999999,12,FALSE),"NO") -> NO | U2: =IF(N2=T2,"SI","NO") -> NO | V2: =IFERROR(VLOOKUP(S2,AFIP!$F$2:$R$999999,13,FALSE),"NO") -> NO | W2: =IF(K2=V2,"SI","NO") -> NO
A3: 000015 | B3: ESCALERAS SIN FIN SOCIEDAD DE HECHO | C3: 80 | D3: 33620532229 | E3: I | F3: 01/10/2025 | G3: NCP | H3: A1 | I3: 000200007977 | J3: 21 | K3: -206388.15 | L3: -170568.72 | M3: 0 | N3: -35819.43 | O3: 0 | P3: 0 | Q3: 0 | R3: 0 | S3: =D3&I3 -> 33620532229000200007977 | T3: =IFERROR(VLOOKUP(S3,AFIP!$F$2:$R$999999,12,FALSE),"NO") -> NO | U3: =IF(N3=T3,"SI","NO") -> NO | V3: =IFERROR(VLOOKUP(S3,AFIP!$F$2:$R$999999,13,FALSE),"NO") -> NO | W3: =IF(K3=V3,"SI","NO") -> NO
A4: 000001 | B4: AKZO NOBEL S.A. - (ALBA & CETOL) | C4: 80 | D4: 30500529454 | E4: I | F4: 03/10/2025 | G4: NCP | H4: A1 | I4: 026700171598 | J4: 21 | K4: -207657.9 | L4: -97841.1 | M4: 0 | N4: -20546.64 | O4: -2935.23 | P4: -2446.03 | Q4: -83888.9 | R4: 0 | S4: =D4&I4 -> 30500529454026700171598 | T4: =IFERROR(VLOOKUP(S4,AFIP!$F$2:$R$999999,12,FALSE),"NO") -> NO | U4: =IF(N4=T4,"SI","NO") -> NO | V4: =IFERROR(VLOOKUP(S4,AFIP!$F$2:$R$999999,13,FALSE),"NO") -> NO | W4: =IF(K4=V4,"SI","NO") -> NO
A5: 000015 | B5: ESCALERAS SIN FIN SOCIEDAD DE HECHO | C5: 80 | D5: 33620532229 | E5: I | F5: 07/10/2025 | G5: NCP | H5: A1 | I5: 000200007985 | J5: 21 | K5: -1506196 | L5: -1244790.1 | M5: 0 | N5: -261405.92 | O5: 0 | P5: 0 | Q5: 0 | R5: 0 | S5: =D5&I5 -> 33620532229000200007985 | T5: =IFERROR(VLOOKUP(S5,AFIP!$F$2:$R$999999,12,FALSE),"NO") -> NO | U5: =IF(N5=T5,"SI","NO") -> NO | V5: =IFERROR(VLOOKUP(S5,AFIP!$F$2:$R$999999,13,FALSE),"NO") -> NO | W5: =IF(K5=V5,"SI","NO") -> NO
A6: 000300 | B6: A A ABRASIVOS ARGENTINOS S.A.I.C. | C6: 80 | D6: 30501044551 | E6: I | F6: 08/10/2025 | G6: NCP | H6: A1 | I6: 000700219976 | J6: 21 | K6: -126936.9 | L6: -30431.38 | M6: 0 | N6: -6390.59 | O6: -912.94 | P6: -760.78 | Q6: -88441.21 | R6: 0 | S6: =D6&I6 -> 30501044551000700219976 | T6: =IFERROR(VLOOKUP(S6,AFIP!$F$2:$R$999999,12,FALSE),"NO") -> NO | U6: =IF(N6=T6,"SI","NO") -> NO | V6: =IFERROR(VLOOKUP(S6,AFIP!$F$2:$R$999999,13,FALSE),"NO") -> NO | W6: =IF(K6=V6,"SI","NO") -> NO
A7: 000001 | B7: AKZO NOBEL S.A. - (ALBA & CETOL) | C7: 80 | D7: 30500529454 | E7: I | F7: 16/10/2025 | G7: NCP | H7: A1 | I7: 026700171749 | J7: 21 | K7: -75705.97 | L7: -62566.92 | M7: 0 | N7: -13139.05 | O7: 0 | P7: 0 | Q7: 0 | R7: 0 | S7: =D7&I7 -> 30500529454026700171749 | T7: =IFERROR(VLOOKUP(S7,AFIP!$F$2:$R$999999,12,FALSE),"NO") -> NO | U7: =IF(N7=T7,"SI","NO") -> NO | V7: =IFERROR(VLOOKUP(S7,AFIP!$F$2:$R$999999,13,FALSE),"NO") -> NO | W7: =IF(K7=V7,"SI","NO") -> NO
A8: 000039 | B8: PREPAN S.A | C8: 80 | D8: 33522734549 | E8: I | F8: 23/10/2025 | G8: NCP | H8: A1 | I8: 002100242470 | J8: 21 | K8: -1668181.7 | L8: -1345307.8 | M8: 0 | N8: -282514.64 | O8: -40359.23 | P8: 0 | Q8: 0 | R8: 0 | S8: =D8&I8 -> 33522734549002100242470 | T8: =IFERROR(VLOOKUP(S8,AFIP!$F$2:$R$999999,12,FALSE),"NO") -> NO | U8: =IF(N8=T8,"SI","NO") -> NO | V8: =IFERROR(VLOOKUP(S8,AFIP!$F$2:$R$999999,13,FALSE),"NO") -> NO | W8: =IF(K8=V8,"SI","NO") -> NO
A9: 000039 | B9: PREPAN S.A | C9: 80 | D9: 33522734549 | E9: I | F9: 23/10/2025 | G9: NCP | H9: A1 | I9: 002100242471 | J9: 21 | K9: -2276867.9 | L9: -1836183.8 | M9: 0 | N9: -385598.6 | O9: -55085.51 | P9: 0 | Q9: 0 | R9: 0 | S9: =D9&I9 -> 33522734549002100242471 | T9: =IFERROR(VLOOKUP(S9,AFIP!$F$2:$R$999999,12,FALSE),"NO") -> NO | U9: =IF(N9=T9,"SI","NO") -> NO | V9: =IFERROR(VLOOKUP(S9,AFIP!$F$2:$R$999999,13,FALSE),"NO") -> NO | W9: =IF(K9=V9,"SI","NO") -> NO
A10: 000039 | B10: PREPAN S.A | C10: 80 | D10: 33522734549 | E10: I | F10: 23/10/2025 | G10: NCP | H10: A1 | I10: 002100242472 | J10: 21 | K10: -5106.02 | L10: -4117.76 | M10: 0 | N10: -864.73 | O10: -123.53 | P10: 0 | Q10: 0 | R10: 0 | S10: =D10&I10 -> 33522734549002100242472 | T10: =IFERROR(VLOOKUP(S10,AFIP!$F$2:$R$999999,12,FALSE),"NO") -> NO | U10: =IF(N10=T10,"SI","NO") -> NO | V10: =IFERROR(VLOOKUP(S10,AFIP!$F$2:$R$999999,13,FALSE),"NO") -> NO | W10: =IF(K10=V10,"SI","NO") -> NO
A11: 000039 | B11: PREPAN S.A | C11: 80 | D11: 33522734549 | E11: I | F11: 23/10/2025 | G11: NCP | H11: A1 | I11: 002100242473 | J11: 21 | K11: -26593.75 | L11: -21446.57 | M11: 0 | N11: -4503.78 | O11: -643.4 | P11: 0 | Q11: 0 | R11: 0 | S11: =D11&I11 -> 33522734549002100242473 | T11: =IFERROR(VLOOKUP(S11,AFIP!$F$2:$R$999999,12,FALSE),"NO") -> NO | U11: =IF(N11=T11,"SI","NO") -> NO | V11: =IFERROR(VLOOKUP(S11,AFIP!$F$2:$R$999999,13,FALSE),"NO") -> NO | W11: =IF(K11=V11,"SI","NO") -> NO
A12: 000039 | B12: PREPAN S.A | C12: 80 | D12: 33522734549 | E12: I | F12: 23/10/2025 | G12: NCP | H12: A1 | I12: 002100242474 | J12: 21 | K12: -383572.04 | L12: -309332.29 | M12: 0 | N12: -64959.78 | O12: -9279.97 | P12: 0 | Q12: 0 | R12: 0 | S12: =D12&I12 -> 33522734549002100242474 | T12: =IFERROR(VLOOKUP(S12,AFIP!$F$2:$R$999999,12,FALSE),"NO") -> NO | U12: =IF(N12=T12,"SI","NO") -> NO | V12: =IFERROR(VLOOKUP(S12,AFIP!$F$2:$R$999999,13,FALSE),"NO") -> NO | W12: =IF(K12=V12,"SI","NO") -> NO
A13: 000102 | B13: FAIP S.A.I.C | C13: 80 | D13: 30523412236 | E13: I | F13: 24/10/2025 | G13: NCP | H13: A1 | I13: 001400012737 | J13: 21 | K13: -1089740 | L13: -900611.59 | M13: 0 | N13: -189128.43 | O13: 0 | P13: 0 | Q13: 0 | R13: 0 | S13: =D13&I13 -> 30523412236001400012737 | T13: =IFERROR(VLOOKUP(S13,AFIP!$F$2:$R$999999,12,FALSE),"NO") -> NO | U13: =IF(N13=T13,"SI","NO") -> NO | V13: =IFERROR(VLOOKUP(S13,AFIP!$F$2:$R$999999,13,FALSE),"NO") -> NO | W13: =IF(K13=V13,"SI","NO") -> NO
... A601: Z9999O | B601: GROSS SERGIO FABIAN | C601: 80 | D601: 23179973219 | E601: M | F601: 30/11/2025 | G601: NF | H601: C | I601: 000200001053 | J601: 0 | K601: 72000 | L601: 0 | M601: 72000 | N601: 0 | O601: 0 | P601: 0 | Q601: 0 | R601: 0 | S601: =D601&I601 -> 23179973219000200001053 | T601: =IFERROR(VLOOKUP(S601,AFIP!$F$2:$R$999999,12,FALSE),"NO") -> NO | U601: =IF(N601=T601,"SI","NO") -> NO | V601: =IFERROR(VLOOKUP(S601,AFIP!$F$2:$R$999999,13,FALSE),"NO") -> NO | W601: =IF(K601=V601,"SI","NO") -> NO

Sheet AFIP
A1: Fecha | B1: Tipo | C1: Punto de Venta | D1: Número Desde | E1: Doc Completo | F1: Unido | G1: Cód. Autorización | H1: Tipo Doc. Emisor | I1: Nro. Doc. Emisor | J1: Denominación Emisor | K1: Tipo Cambio | L1: Moneda | M1: Imp. Neto Gravado | N1: Imp. Neto No Gravado | O1: Imp. Op. Exentas | P1: Otros Tributos | Q1: IVA | R1: Imp. Total
A2: 45962 | B2: 1 | C2: 3 | D2: 109597 | E2: =TEXT(C2,"0000")&TEXT(D2,"00000000") -> 000300109597 | F2: =I2&E2 -> 30708762373000300109597 | G2: 75443659659757 | H2: 80 | I2: 30708762373 | J2: FIDEICOMISO ENTRE OFEK S.A. , OSVALDO BESNOSOFF Y OTROS | K2: 1 | L2: $ | M2: 27685.95 | N2: 0 | O2: 0 | P2: 0 | Q2: 5814.05 | R2: 33500
A3: 45962 | B3: 1 | C3: 3 | D3: 15537 | E3: =TEXT(C3,"0000")&TEXT(D3,"00000000") -> 000300015537 | F3: =I3&E3 -> 30715919792000300015537 | G3: 75442086050641 | H3: 80 | I3: 30715919792 | J3: CAPASITIO S.A.S. | K3: 1 | L3: $ | M3: 163509.55 | N3: 0 | O3: 0 | P3: 0 | Q3: 34337.01 | R3: 197846.56
A4: 45962 | B4: 1 | C4: 24 | D4: 12051 | E4: =TEXT(C4,"0000")&TEXT(D4,"00000000") -> 002400012051 | F4: =I4&E4 -> 33681952239002400012051 | G4: 75449067401105 | H4: 80 | I4: 33681952239 | J4: TELECABLE COLOR RINCON SRL | K4: 1 | L4: $ | M4: 14876.03 | N4: 0 | O4: 0 | P4: 0 | Q4: 3123.97 | R4: 18000
A5: 45962 | B5: 1 | C5: 2 | D5: 66062 | E5: =TEXT(C5,"0000")&TEXT(D5,"00000000") -> 000200066062 | F5: =I5&E5 -> 30708506237000200066062 | G5: 75447084285249 | H5: 80 | I5: 30708506237 | J5: EXPRESO 3 C SRL | K5: 1 | L5: $ | M5: 130709.95 | N5: 0 | O5: 0 | P5: 0 | Q5: 27449.09 | R5: 158159.04
A6: 45962 | B6: 1 | C6: 711 | D6: 7789834 | E6: =TEXT(C6,"0000")&TEXT(D6,"00000000") -> 071107789834 | F6: =I6&E6 -> 30677237119071107789834 | G6: 35439383462793 | H6: 80 | I6: 30677237119 | J6: AUTOPISTAS DEL SOL S A | K6: 1 | L6: $ | M6: 2657.75 | N6: 0 | O6: 79.73 | P6: 159.47 | Q6: 558.13 | R6: 3455.08
A7: 45962 | B7: 1 | C7: 629 | D7: 6608454 | E7: =TEXT(C7,"0000")&TEXT(D7,"00000000") -> 062906608454 | F7: =I7&E7 -> 30663498513062906608454 | G7: 35433970133027 | H7: 80 | I7: 30663498513 | J7: GRUPO CONCESIONARIO DEL OESTE SA | K7: 1 | L7: $ | M7: 3466.56 | N7: 0 | O7: 0 | P7: 207.99 | Q7: 727.98 | R7: 4402.53
A8: 45962 | B8: 1 | C8: 2 | D8: 10332 | E8: =TEXT(C8,"0000")&TEXT(D8,"00000000") -> 000200010332 | F8: =I8&E8 -> 30709715395000200010332 | G8: 75455673770393 | H8: 80 | I8: 30709715395 | J8: METROTEC S. A. | K8: 1 | L8: $ | M8: 1752300 | N8: 0 | O8: 0 | P8: 0 | Q8: 367983 | R8: 2120283
A9: 45962 | B9: 1 | C9: 2 | D9: 10333 | E9: =TEXT(C9,"0000")&TEXT(D9,"00000000") -> 000200010333 | F9: =I9&E9 -> 30709715395000200010333 | G9: 75455673877711 | H9: 80 | I9: 30709715395 | J9: METROTEC S. A. | K9: 1 | L9: $ | M9: 2570040 | N9: 0 | O9: 0 | P9: 0 | Q9: 539708.4 | R9: 3109748.4
A10: 45962 | B10: 1 | C10: 2 | D10: 10267 | E10: =TEXT(C10,"0000")&TEXT(D10,"00000000") -> 000200010267 | F10: =I10&E10 -> 30709715395000200010267 | G10: 75455672570597 | H10: 80 | I10: 30709715395 | J10: METROTEC S. A. | K10: 1 | L10: $ | M10: 1351100 | N10: 0 | O10: 0 | P10: 0 | Q10: 283731 | R10: 1634831
A11: 45962 | B11: 1 | C11: 9 | D11: 32 | E11: =TEXT(C11,"0000")&TEXT(D11,"00000000") -> 000900000032 | F11: =I11&E11 -> 27144014656000900000032 | G11: 75446090184621 | H11: 80 | I11: 27144014656 | J11: RICOBELLI ROSANA | K11: 1 | L11: $ | M11: 1150000 | N11: 0 | O11: 0 | P11: 0 | Q11: 241500 | R11: 1391500
A12: 45962 | B12: 6 | C12: 5 | D12: 10700 | E12: =TEXT(C12,"0000")&TEXT(D12,"00000000") -> 000500010700 | F12: =I12&E12 -> 20253290960000500010700 | G12: 75450444440972 | H12: 80 | I12: 20253290960 | J12: SACCONE SIMON | K12: 1 | L12: $ | M12: 0 | N12: 0 | O12: 0 | P12: 0 | Q12: 0 | R12: 120000
A13: 45962 | B13: 11 | C13: 3 | D13: 13 | E13: =TEXT(C13,"0000")&TEXT(D13,"00000000") -> 000300000013 | F13: =I13&E13 -> 27286259508000300000013 | G13: 75448989406969 | H13: 80 | I13: 27286259508 | J13: CRAVAREZZA RENATA | K13: 1 | L13: $ | M13: 0 | N13: 0 | O13: 0 | P13: 0 | Q13: 0 | R13: 1590000
... A29: 45964 | B29: 1 | C29: 1 | D29: 866 | E29: =TEXT(C29,"0000")&TEXT(D29,"00000000") -> 000100000866 | F29: =I29&E29 -> 30716314320000100000866 | G29: 75440294376563 | H29: 80 | I29: 30716314320 | J29: CONDOMINIO DE YPPOLITO DANIEL OSVALDO Y HESSEL LILIANA | K29: 1 | L29: $ | M29: 1035000 | N29: 0 | O29: 0 | P29: 0 | Q29: 217350 | R29: 1252350
A30: 45964 | B30: 1 | C30: 215 | D30: 100298 | E30: =TEXT(C30,"0000")&TEXT(D30,"00000000") -> 021500100298 | F30: =I30&E30 -> 30500529071021500100298 | G30: 35431670074949 | H30: 80 | I30: 30500529071 | J30: SAINT-GOBAIN ARGENTINA SA | K30: 1 | L30: $ | M30: 10778729 | P30: 592830.09 | Q30: 2263533.1 | R30: 13635092
A31: 45964 | B31: 3 | C31: 9 | D31: 27 | E31: =TEXT(C31,"0000")&TEXT(D31,"00000000") -> 000900000027 | F31: =I31&E31 -> 20335001932000900000027 | G31: 75442322873115 | H31: 80 | I31: 20335001932 | J31: VILLATA FERNANDO ARIEL | K31: 1 | L31: $ | M31: 12727.27 | N31: 0 | O31: 0 | P31: 0 | Q31: 2672.73 | R31: 15400
A32: 45964 | B32: 3 | C32: 2 | D32: 1444 | E32: =TEXT(C32,"0000")&TEXT(D32,"00000000") -> 000200001444 | F32: =I32&E32 -> 30714379468000200001444 | G32: 75448370338614 | H32: 80 | I32: 30714379468 | J32: PAINT & DETAIL S.R.L. | K32: 1 | L32: $ | M32: 3819 | N32: 0 | O32: 0 | P32: 0 | Q32: 801.99 | R32: 4620.99
A33: 45964 | B33: 3 | C33: 3 | D33: 847 | E33: =TEXT(C33,"0000")&TEXT(D33,"00000000") -> 000300000847 | F33: =I33&E33 -> 23174473919000300000847 | G33: 75449282856431 | H33: 80 | I33: 23174473919 | J33: TARIS JORGE LUIS | K33: 1 | L33: $ | M33: 46910.61 | N33: 0 | O33: 0 | P33: 0 | Q33: 9851.23 | R33: 56761.84
A34: 45964 | B34: 3 | C34: 5 | D34: 1875 | E34: =TEXT(C34,"0000")&TEXT(D34,"00000000") -> 000500001875 | F34: =I34&E34 -> 30707509976000500001875 | G34: 75446334904941 | H34: 80 | I34: 30707509976 | J34: ANGA S.A. | K34: 1 | L34: $ | M34: 64214.18 | N34: 0 | O34: 0 | P34: 0 | Q34: 13484.98 | R34: 77699.16
A35: 45964 | B35: 3 | C35: 201 | D35: 269929 | E35: =TEXT(C35,"0000")&TEXT(D35,"00000000") -> 020100269929 | F35: =I35&E35 -> 30500529071020100269929 | G35: 35431670074949 | H35: 80 | I35: 30500529071 | J35: SAINT-GOBAIN ARGENTINA SA | K35: 1 | L35: $ | M35: 538936.43 | P35: 16168.09 | Q35: 113176.65 | R35: 668281.19
A36: 45964 | B36: 6 | C36: 9 | D36: 19924 | E36: =TEXT(C36,"0000")&TEXT(D36,"00000000") -> 000900019924 | F36: =I36&E36 -> 20216414897000900019924 | G36: 75447317985785 | H36: 80 | I36: 20216414897 | J36: LONGONI FABIAN RAUL | K36: 1 | L36: $ | M36: 0 | N36: 0 | O36: 0 | P36: 0 | Q36: 0 | R36: 25767.02
A37: 45964 | B37: 11 | C37: 100 | D37: 1325670 | E37: =TEXT(C37,"0000")&TEXT(D37,"00000000") -> 010001325670 | F37: =I37&E37 -> 30567510138010001325670 | G37: 75438585782815 | H37: 80 | I37: 30567510138 | J37: ASOCIACION MUTUAL RURALISTA | K37: 1 | L37: $ | M37: 0 | N37: 0 | O37: 0 | P37: 0 | Q37: 0 | R37: 842432
A38: 45964 | B38: 11 | C38: 3 | D38: 143 | E38: =TEXT(C38,"0000")&TEXT(D38,"00000000") -> 000300000143 | F38: =I38&E38 -> 23292606389000300000143 | G38: 75449330606094 | H38: 80 | I38: 23292606389 | J38: CAPISANO ENRIQUE | K38: 1 | L38: $ | M38: 0 | N38: 0 | O38: 0 | P38: 0 | Q38: 0 | R38: 120000
A39: 45964 | B39: 11 | C39: 3 | D39: 918 | E39: =TEXT(C39,"0000")&TEXT(D39,"00000000") -> 000300000918 | F39: =I39&E39 -> 20314191294000300000918 | G39: 75444307728486 | H39: 80 | I39: 20314191294 | J39: BERTRAM JOSE LUIS | K39: 1 | L39: $ | M39: 0 | N39: 0 | O39: 0 | P39: 0 | Q39: 0 | R39: 50000
A40: 45964 | B40: 11 | C40: 1 | D40: 119 | E40: =TEXT(C40,"0000")&TEXT(D40,"00000000") -> 000100000119 | F40: =I40&E40 -> 20177222802000100000119 | G40: 75442408496530 | H40: 80 | I40: 20177222802 | J40: MULE JAVIER JOSE | K40: 1 | L40: $ | M40: 0 | N40: 0 | O40: 0 | P40: 0 | Q40: 0 | R40: 1212100
A41: 45964 | B41: 11 | C41: 1 | D41: 199 | E41: =TEXT(C41,"0000")&TEXT(D41,"00000000") -> 000100000199 | F41: =I41&E41 -> 27181583644000100000199 | G41: 75444392803487 | H41: 80 | I41: 27181583644 | J41: MIGNOLA ADRIANA ESTELA | K41: 1 | L41: $ | M41: 0 | N41: 0 | O41: 0 | P41: 0 | Q41: 0 | R41: 467000
A42: 45964 | B42: 11 | C42: 1 | D42: 98 | E42: =TEXT(C42,"0000")&TEXT(D42,"00000000") -> 000100000098 | F42: =I42&E42 -> 27301695689000100000098 | G42: 75459445457776 | H42: 80 | I42: 27301695689 | J42: CENA VANESA | K42: 1 | L42: $ | M42: 0 | N42: 0 | O42: 0 | P42: 0 | Q42: 0 | R42: 1625000
A43: 45964 | B43: 15 | C43: 2 | D43: 3003 | E43: =TEXT(C43,"0000")&TEXT(D43,"00000000") -> 000200003003 | F43: =I43&E43 -> 30681948623000200003003 | G43: 75433525242533 | H43: 80 | I43: 30681948623 | J43: ASOCIACION COOPERADORA POLICIAL DE ESPERANZA DEPARTAMENTO LAS COLONIAS PROVINCIA DE SANTA FE | K43: 1 | L43: $ | M43: 0 | N43: 0 | O43: 0 | P43: 0 | Q43: 0 | R43: 10000
A44: 45965 | B44: 1 | C44: 19 | D44: 3764 | E44: =TEXT(C44,"0000")&TEXT(D44,"00000000") -> 001900003764 | F44: =I44&E44 -> 30601652044001900003764 | G44: 75444439421858 | H44: 80 | I44: 30601652044 | J44: ELECTRICIDAD COLOMBO S.A. | K44: 1 | L44: $ | M44: 2588.32 | N44: 0 | O44: 0 | P44: 0 | Q44: 543.55 | R44: 3131.87
A45: 45965 | B45: 1 | C45: 4 | D45: 17859 | E45: =TEXT(C45,"0000")&TEXT(D45,"00000000") -> 000400017859 | F45: =I45&E45 -> 20062436965000400017859 | G45: 75445473271275 | H45: 80 | I45: 20062436965 | J45: BOTTAI ALBERTO ARTURO | K45: 1 | L45: $ | M45: 915996.85 | N45: 0 | O45: 0 | P45: 0 | Q45: 192359.34 | R45: 1108356.2
A46: 45965 | B46: 1 | C46: 5 | D46: 1693 | E46: =TEXT(C46,"0000")&TEXT(D46,"00000000") -> 000500001693 | F46: =I46&E46 -> 27171610163000500001693 | G46: 75443520227263 | H46: 80 | I46: 27171610163 | J46: COMBIN SONIA NANCI | K46: 1 | L46: $ | M46: 13223.14 | N46: 0 | O46: 0 | P46: 0 | Q46: 2776.86 | R46: 16000
A47: 45965 | B47: 1 | C47: 18 | D47: 9317 | E47: =TEXT(C47,"0000")&TEXT(D47,"00000000") -> 001800009317 | F47: =I47&E47 -> 30601652044001800009317 | G47: 75444498650600 | H47: 80 | I47: 30601652044 | J47: ELECTRICIDAD COLOMBO S.A. | K47: 1 | L47: $ | M47: 63022.4 | N47: 0 | O47: 0 | P47: 0 | Q47: 13234.7 | R47: 76257.1
... A62: 45965 | B62: 1 | C62: 2 | D62: 2262 | E62: =TEXT(C62,"0000")&TEXT(D62,"00000000") -> 000200002262 | F62: =I62&E62 -> 20201399298000200002262 | G62: 75448453486360 | H62: 80 | I62: 20201399298 | J62: KLOSTER MARCELO ESTEBAN | K62: 1 | L62: $ | M62: 396496.76 | N62: 0 | O62: 0 | P62: 0 | Q62: 83264.32 | R62: 479761.07
A63: 45965 | B63: 1 | C63: 215 | D63: 100311 | E63: =TEXT(C63,"0000")&TEXT(D63,"00000000") -> 021500100311 | F63: =I63&E63 -> 30500529071021500100311 | G63: 35431670074949 | H63: 80 | I63: 30500529071 | J63: SAINT-GOBAIN ARGENTINA SA | K63: 1 | L63: $ | M63: 24359540 | P63: 1339774.7 | Q63: 5115503.4 | R63: 30814818
A64: 45965 | B64: 1 | C64: 215 | D64: 100312 | E64: =TEXT(C64,"0000")&TEXT(D64,"00000000") -> 021500100312 | F64: =I64&E64 -> 30500529071021500100312 | G64: 35431670074949 | H64: 80 | I64: 30500529071 | J64: SAINT-GOBAIN ARGENTINA SA | K64: 1 | L64: $ | M64: 198615.81 | P64: 10923.88 | Q64: 41709.32 | R64: 251249.01
A65: 45965 | B65: 3 | C65: 1203 | D65: 362 | E65: =TEXT(C65,"0000")&TEXT(D65,"00000000") -> 120300000362 | F65: =I65&E65 -> 30708492945120300000362 | G65: 75445446847861 | H65: 80 | I65: 30708492945 | J65: SINIS S. A. | K65: 1345.0068 | L65: USD | M65: 293.58 | N65: 0 | O65: 0 | P65: 0 | Q65: 61.65 | R65: 355.23
A66: 45965 | B66: 3 | C66: 333 | D66: 11234 | E66: =TEXT(C66,"0000")&TEXT(D66,"00000000") -> 033300011234 | F66: =I66&E66 -> 30646512952033300011234 | G66: 35432150758787 | H66: 80 | I66: 30646512952 | J66: PINTURERIAS REX S A | K66: 1 | L66: $ | M66: 71574.89 | N66: 0 | O66: 0 | P66: 0 | Q66: 15030.73 | R66: 86605.62
A67: 45965 | B67: 3 | C67: 333 | D67: 11236 | E67: =TEXT(C67,"0000")&TEXT(D67,"00000000") -> 033300011236 | F67: =I67&E67 -> 30646512952033300011236 | G67: 35432150758787 | H67: 80 | I67: 30646512952 | J67: PINTURERIAS REX S A | K67: 1 | L67: $ | M67: 41008.39 | N67: 0 | O67: 0 | P67: 0 | Q67: 8611.76 | R67: 49620.15
A68: 45965 | B68: 3 | C68: 333 | D68: 11237 | E68: =TEXT(C68,"0000")&TEXT(D68,"00000000") -> 033300011237 | F68: =I68&E68 -> 30646512952033300011237 | G68: 35432150758787 | H68: 80 | I68: 30646512952 | J68: PINTURERIAS REX S A | K68: 1 | L68: $ | M68: 34708.93 | N68: 0 | O68: 0 | P68: 0 | Q68: 7288.88 | R68: 41997.81
A69: 45965 | B69: 3 | C69: 32 | D69: 164767 | E69: =TEXT(C69,"0000")&TEXT(D69,"00000000") -> 003200164767 | F69: =I69&E69 -> 30621181838003200164767 | G69: 75448522531658 | H69: 80 | I69: 30621181838 | J69: DISAL S A | K69: 1 | L69: $ | M69: 45991331 | P69: 0 | Q69: 9658179.4 | R69: 55649510
A70: 45965 | B70: 3 | C70: 21 | D70: 242996 | E70: =TEXT(C70,"0000")&TEXT(D70,"00000000") -> 002100242996 | F70: =I70&E70 -> 33522734549002100242996 | G70: 35439367218964 | H70: 80 | I70: 33522734549 | J70: PREPAN SOCIEDAD ANONIMA | K70: 1 | L70: $ | M70: 7636792.6 | N70: 0 | O70: 0 | P70: 0 | Q70: 1603726.4 | R70: 9240519
A71: 45965 | B71: 3 | C71: 201 | D71: 269948 | E71: =TEXT(C71,"0000")&TEXT(D71,"00000000") -> 020100269948 | F71: =I71&E71 -> 30500529071020100269948 | G71: 35431670074949 | H71: 80 | I71: 30500529071 | J71: SAINT-GOBAIN ARGENTINA SA | K71: 1 | L71: $ | M71: 1217977 | P71: 36539.31 | Q71: 255775.17 | R71: 1510291.5
A72: 45965 | B72: 3 | C72: 201 | D72: 269949 | E72: =TEXT(C72,"0000")&TEXT(D72,"00000000") -> 020100269949 | F72: =I72&E72 -> 30500529071020100269949 | G72: 35431670074949 | H72: 80 | I72: 30500529071 | J72: SAINT-GOBAIN ARGENTINA SA | K72: 1 | L72: $ | M72: 9930.81 | P72: 297.92 | Q72: 2085.47 | R72: 12314.18
A73: 45965 | B73: 11 | C73: 1 | D73: 262 | E73: =TEXT(C73,"0000")&TEXT(D73,"00000000") -> 000100000262 | F73: =I73&E73 -> 20399678553000100000262 | G73: 75443556199590 | H73: 80 | I73: 20399678553 | J73: SUÃ‘E VALENTIN | K73: 1 | L73: $ | M73: 0 | N73: 0 | O73: 0 | P73: 0 | Q73: 0 | R73: 668000
A74: 45965 | B74: 11 | C74: 1 | D74: 253 | E74: =TEXT(C74,"0000")&TEXT(D74,"00000000") -> 000100000253 | F74: =I74&E74 -> 20377100965000100000253 | G74: 75445556449759 | H74: 80 | I74: 20377100965 | J74: SUÃ‘E AGUSTIN | K74: 1 | L74: $ | M74: 0 | N74: 0 | O74: 0 | P74: 0 | Q74: 0 | R74: 668000
A75: 45965 | B75: 11 | C75: 3 | D75: 415 | E75: =TEXT(C75,"0000")&TEXT(D75,"00000000") -> 000300000415 | F75: =I75&E75 -> 23345365389000300000415 | G75: 75449556677875 | H75: 80 | I75: 23345365389 | J75: SUÃ‘E LAUTARO | K75: 1 | L75: $ | M75: 0 | N75: 0 | O75: 0 | P75: 0 | Q75: 0 | R75: 668000
A76: 45965 | B76: 15 | C76: 3 | D76: 721 | E76: =TEXT(C76,"0000")&TEXT(D76,"00000000") -> 000300000721 | F76: =I76&E76 -> 30710468695000300000721 | G76: 75445488258991 | H76: 80 | I76: 30710468695 | J76: INSTITUTO MUNICIPAL DE INVERSION | K76: 1 | L76: $ | M76: 0 | N76: 0 | O76: 0 | P76: 0 | Q76: 0 | R76: 3464.1
A77: 45965 | B77: 15 | C77: 3 | D77: 712 | E77: =TEXT(C77,"0000")&TEXT(D77,"00000000") -> 000300000712 | F77: =I77&E77 -> 30710468695000300000712 | G77: 75445484292273 | H77: 80 | I77: 30710468695 | J77: INSTITUTO MUNICIPAL DE INVERSION | K77: 1 | L77: $ | M77: 0 | N77: 0 | O77: 0 | P77: 0 | Q77: 0 | R77: 87643.6
A78: 45966 | B78: 1 | C78: 2 | D78: 9869 | E78: =TEXT(C78,"0000")&TEXT(D78,"00000000") -> 000200009869 | F78: =I78&E78 -> 30712091793000200009869 | G78: 75453631239177 | H78: 80 | I78: 30712091793 | J78: LOGO GROUP S.A. | K78: 1 | L78: $ | M78: 3570000 | N78: 0 | O78: 0 | P78: 0 | Q78: 749700 | R78: 4319700
A79: 45966 | B79: 1 | C79: 8 | D79: 87934 | E79: =TEXT(C79,"0000")&TEXT(D79,"00000000") -> 000800087934 | F79: =I79&E79 -> 30536184054000800087934 | G79: 75454658511828 | H79: 80 | I79: 30536184054 | J79: GRANDES ALMACENES ESPERANZA S A I Y C | K79: 1 | L79: $ | M79: 253061.26 | N79: 0 | O79: 0 | P79: 6326.53 | Q79: 53142.87 | R79: 312530.66
A80: 45966 | B80: 1 | C80: 4 | D80: 17885 | E80: =TEXT(C80,"0000")&TEXT(D80,"00000000") -> 000400017885 | F80: =I80&E80 -> 20062436965000400017885 | G80: 75455655786213 | H80: 80 | I80: 20062436965 | J80: BOTTAI ALBERTO ARTURO | K80: 1 | L80: $ | M80: 1994509.3 | N80: 0 | O80: 37744.76 | P80: 0 | Q80: 418846.94 | R80: 2451101
A81: 45966 | B81: 1 | C81: 2 | D81: 10331 | E81: =TEXT(C81,"0000")&TEXT(D81,"00000000") -> 000200010331 | F81: =I81&E81 -> 30642674567000200010331 | G81: 75457807793544 | H81: 80 | I81: 30642674567 | J81: CHIASA S R L | K81: 1 | L81: $ | M81: 714359.56 | N81: 0 | O81: 0 | P81: 0 | Q81: 150015.51 | R81: 864375.07
A82: 45966 | B82: 1 | C82: 2 | D82: 10328 | E82: =TEXT(C82,"0000")&TEXT(D82,"00000000") -> 000200010328 | F82: =I82&E82 -> 30642674567000200010328 | G82: 75457795888458 | H82: 80 | I82: 30642674567 | J82: CHIASA S R L | K82: 1 | L82: $ | M82: 13968.23 | N82: 0 | O82: 0 | P82: 0 | Q82: 2933.33 | R82: 16901.56
A83: 45966 | B83: 1 | C83: 2 | D83: 10330 | E83: =TEXT(C83,"0000")&TEXT(D83,"00000000") -> 000200010330 | F83: =I83&E83 -> 30642674567000200010330 | G83: 75457799260558 | H83: 80 | I83: 30642674567 | J83: CHIASA S R L | K83: 1 | L83: $ | M83: 60216.25 | N83: 0 | O83: 0 | P83: 0 | Q83: 12645.41 | R83: 72861.66
A84: 45966 | B84: 1 | C84: 2 | D84: 10326 | E84: =TEXT(C84,"0000")&TEXT(D84,"00000000") -> 000200010326 | F84: =I84&E84 -> 30642674567000200010326 | G84: 75457772492996 | H84: 80 | I84: 30642674567 | J84: CHIASA S R L | K84: 1 | L84: $ | M84: 132068.36 | N84: 0 | O84: 0 | P84: 0 | Q84: 27734.36 | R84: 159802.72
... A93: 45966 | B93: 1 | C93: 1 | D93: 796 | E93: =TEXT(C93,"0000")&TEXT(D93,"00000000") -> 000100000796 | F93: =I93&E93 -> 30715231715000100000796 | G93: 75455600181499 | H93: 80 | I93: 30715231715 | J93: VILLATA GISELA E., VILLATA DIEGO H., VILLATA FERNANDO A., VILLATA HORACIO J. Y VILLATA KAREN B. SOCI | K93: 1 | L93: $ | M93: 762000 | N93: 0 | O93: 0 | P93: 0 | Q93: 160020 | R93: 922020
A94: 45966 | B94: 1 | C94: 32 | D94: 254165 | E94: =TEXT(C94,"0000")&TEXT(D94,"00000000") -> 003200254165 | F94: =I94&E94 -> 30621181838003200254165 | G94: 75458719693970 | H94: 80 | I94: 30621181838 | J94: DISAL S A | K94: 1 | L94: $ | M94: 352044.33 | P94: 0 | Q94: 73929.31 | R94: 425973.63
A95: 45966 | B95: 1 | C95: 32 | D95: 254166 | E95: =TEXT(C95,"0000")&TEXT(D95,"00000000") -> 003200254166 | F95: =I95&E95 -> 30621181838003200254166 | G95: 75458719727302 | H95: 80 | I95: 30621181838 | J95: DISAL S A | K95: 1 | L95: $ | M95: 402265.9 | P95: 0 | Q95: 84475.84 | R95: 486741.73
A96: 45966 | B96: 2 | C96: 11 | D96: 2 | E96: =TEXT(C96,"0000")&TEXT(D96,"00000000") -> 001100000002 | F96: =I96&E96 -> 30526148246001100000002 | G96: 75456677619349 | H96: 80 | I96: 30526148246 | J96: CASA BODE S. R. L. | K96: 1 | L96: $ | M96: 227150.4 | N96: 0 | O96: 0 | P96: 0 | Q96: 47701.58 | R96: 274851.98
A97: 45966 | B97: 11 | C97: 8 | D97: 1379 | E97: =TEXT(C97,"0000")&TEXT(D97,"00000000") -> 000800001379 | F97: =I97&E97 -> 30699881100000800001379 | G97: 75450673159739 | H97: 80 | I97: 30699881100 | J97: FUNDACION INSTITUTO TECNOLOGICO EL MOLINO | K97: 1 | L97: $ | M97: 0 | N97: 0 | O97: 0 | P97: 0 | Q97: 0 | R97: 348124.8
A98: 45966 | B98: 11 | C98: 4 | D98: 10152 | E98: =TEXT(C98,"0000")&TEXT(D98,"00000000") -> 000400010152 | F98: =I98&E98 -> 30710244274000400010152 | G98: 75454721307272 | H98: 80 | I98: 30710244274 | J98: CAMARA ARGENTINA DE PINTURERIAS | K98: 1 | L98: $ | M98: 0 | N98: 0 | O98: 0 | P98: 0 | Q98: 0 | R98: 187000
A99: 45966 | B99: 11 | C99: 3 | D99: 252 | E99: =TEXT(C99,"0000")&TEXT(D99,"00000000") -> 000300000252 | F99: =I99&E99 -> 20220874568000300000252 | G99: 75458631445329 | H99: 80 | I99: 20220874568 | J99: CORONEL ADRIAN DANILO | K99: 1 | L99: $ | M99: 0 | N99: 0 | O99: 0 | P99: 0 | Q99: 0 | R99: 440000
A100: 45966 | B100: 11 | C100: 2 | D100: 38 | E100: =TEXT(C100,"0000")&TEXT(D100,"00000000") -> 000200000038 | F100: =I100&E100 -> 20266044535000200000038 | G100: 75455610612478 | H100: 80 | I100: 20266044535 | J100: MALDONADO FERNANDO DANIEL | K100: 1 | L100: $ | M100: 0 | N100: 0 | O100: 0 | P100: 0 | Q100: 0 | R100: 460000
A101: 45966 | B101: 11 | C101: 3 | D101: 495 | E101: =TEXT(C101,"0000")&TEXT(D101,"00000000") -> 000300000495 | F101: =I101&E101 -> 20302918768000300000495 | G101: 75458601519009 | H101: 80 | I101: 20302918768 | J101: ENGLER ALEJANDRO | K101: 1 | L101: $ | M101: 0 | N101: 0 | O101: 0 | P101: 0 | Q101: 0 | R101: 140000
A102: 45967 | B102: 1 | C102: 2 | D102: 39108 | E102: =TEXT(C102,"0000")&TEXT(D102,"00000000") -> 000200039108 | F102: =I102&E102 -> 20076351679000200039108 | G102: 75459758529632 | H102: 80 | I102: 20076351679 | J102: WILLINER JUAN JOSE | K102: 1 | L102: $ | M102: 99000 | N102: 0 | O102: 0 | P102: 0 | Q102: 20790 | R102: 119790
A103: 45967 | B103: 1 | C103: 2 | D103: 26237 | E103: =TEXT(C103,"0000")&TEXT(D103,"00000000") -> 000200026237 | F103: =I103&E103 -> 27064866163000200026237 | G103: 75453789688184 | H103: 80 | I103: 27064866163 | J103: BOSCH GLADYS MARIA DEL HUE | K103: 1 | L103: $ | M103: 1070000 | N103: 54866 | O103: 0 | P103: 0 | Q103: 224700 | R103: 1349566
A104: 45967 | B104: 1 | C104: 3 | D104: 48617 | E104: =TEXT(C104,"0000")&TEXT(D104,"00000000") -> 000300048617 | F104: =I104&E104 -> 30708216298000300048617 | G104: 75458824346413 | H104: 80 | I104: 30708216298 | J104: METALURGICA J.M.D. S.A. | K104: 1 | L104: $ | M104: 1467027.3 | N104: 0 | O104: 0 | P104: 0 | Q104: 308075.74 | R104: 1775103.1
A105: 45967 | B105: 1 | C105: 5 | D105: 15214 | E105: =TEXT(C105,"0000")&TEXT(D105,"00000000") -> 000500015214 | F105: =I105&E105 -> 23066238849000500015214 | G105: 75459813244550 | H105: 80 | I105: 23066238849 | J105: SUCESION DE RIVERA EDUARDO | K105: 1 | L105: $ | M105: 33057.85 | N105: 0 | O105: 0 | P105: 0 | Q105: 6942.15 | R105: 40000
A106: 45967 | B106: 1 | C106: 3 | D106: 1146 | E106: =TEXT(C106,"0000")&TEXT(D106,"00000000") -> 000300001146 | F106: =I106&E106 -> 30717292355000300001146 | G106: 75455819645079 | H106: 80 | I106: 30717292355 | J106: NUESTRO S. A. S. | K106: 1 | L106: $ | M106: 24628.1 | N106: 0 | O106: 0 | P106: 0 | Q106: 5171.9 | R106: 29800
A107: 45967 | B107: 1 | C107: 333 | D107: 124879 | E107: =TEXT(C107,"0000")&TEXT(D107,"00000000") -> 033300124879 | F107: =I107&E107 -> 30646512952033300124879 | G107: 35432150758787 | H107: 80 | I107: 30646512952 | J107: PINTURERIAS REX S A | K107: 1 | L107: $ | M107: 7749414.3 | N107: 0 | O107: 0 | P107: 0 | Q107: 1627377 | R107: 9376791.4
... A114: 45967 | B114: 1 | C114: 267 | D114: 906384 | E114: =TEXT(C114,"0000")&TEXT(D114,"00000000") -> 026700906384 | F114: =I114&E114 -> 30500529454026700906384 | G114: 75454853667125 | H114: 80 | I114: 30500529454 | J114: AKZO NOBEL ARGENTINA S.A | K114: 1 | L114: $ | M114: 523308.57 | N114: 0 | O114: 0 | P114: 28781.97 | Q114: 109894.8 | R114: 661985.37
A115: 45967 | B115: 1 | C115: 215 | D115: 100374 | E115: =TEXT(C115,"0000")&TEXT(D115,"00000000") -> 021500100374 | F115: =I115&E115 -> 30500529071021500100374 | G115: 35431670074949 | H115: 80 | I115: 30500529071 | J115: SAINT-GOBAIN ARGENTINA SA | K115: 1 | L115: $ | M115: 6574624.9 | P115: 361604.23 | Q115: 1380671.2 | R115: 8316900.1
A116: 45967 | B116: 1 | C116: 215 | D116: 100377 | E116: =TEXT(C116,"0000")&TEXT(D116,"00000000") -> 021500100377 | F116: =I116&E116 -> 30500529071021500100377 | G116: 35431670074949 | H116: 80 | I116: 30500529071 | J116: SAINT-GOBAIN ARGENTINA SA | K116: 1 | L116: $ | M116: 848514.67 | P116: 46668.31 | Q116: 178188.08 | R116: 1073371.1
A117: 45967 | B117: 3 | C117: 201 | D117: 270079 | E117: =TEXT(C117,"0000")&TEXT(D117,"00000000") -> 020100270079 | F117: =I117&E117 -> 30500529071020100270079 | G117: 35431670074949 | H117: 80 | I117: 30500529071 | J117: SAINT-GOBAIN ARGENTINA SA | K117: 1 | L117: $ | M117: 42425.71 | P117: 1272.77 | Q117: 8909.4 | R117: 52607.9
A118: 45967 | B118: 11 | C118: 2 | D118: 501 | E118: =TEXT(C118,"0000")&TEXT(D118,"00000000") -> 000200000501 | F118: =I118&E118 -> 27173680614000200000501 | G118: 75454767489137 | H118: 80 | I118: 27173680614 | J118: ZAVALA MARCELA GLADIS | K118: 1 | L118: $ | M118: 0 | N118: 0 | O118: 0 | P118: 0 | Q118: 0 | R118: 581160
A119: 45968 | B119: 1 | C119: 3 | D119: 121 | E119: =TEXT(C119,"0000")&TEXT(D119,"00000000") -> 000300000121 | F119: =I119&E119 -> 30717903524000300000121 | G119: 75454903547118 | H119: 80 | I119: 30717903524 | J119: PANADERIA LA ALIANZA S. R. L. | K119: 1 | L119: $ | M119: 25289.26 | N119: 0 | O119: 0 | P119: 0 | Q119: 5310.74 | R119: 30600
A120: 45968 | B120: 1 | C120: 4 | D120: 2656 | E120: =TEXT(C120,"0000")&TEXT(D120,"00000000") -> 000400002656 | F120: =I120&E120 -> 20335001932000400002656 | G120: 75452919100349 | H120: 80 | I120: 20335001932 | J120: VILLATA FERNANDO ARIEL | K120: 1 | L120: $ | M120: 3611.57 | N120: 0 | O120: 0 | P120: 0 | Q120: 758.43 | R120: 4370
A121: 45968 | B121: 1 | C121: 25 | D121: 54028 | E121: =TEXT(C121,"0000")&TEXT(D121,"00000000") -> 002500054028 | F121: =I121&E121 -> 30543035064002500054028 | G121: 75454919248708 | H121: 80 | I121: 30543035064 | J121: BARALE S.A. | K121: 1 | L121: $ | M121: 72727.25 | N121: 0 | O121: 0 | P121: 11999.99 | Q121: 15272.72 | R121: 99999.96
A122: 45968 | B122: 1 | C122: 18 | D122: 9346 | E122: =TEXT(C122,"0000")&TEXT(D122,"00000000") -> 001800009346 | F122: =I122&E122 -> 30601652044001800009346 | G122: 75454970291574 | H122: 80 | I122: 30601652044 | J122: ELECTRICIDAD COLOMBO S.A. | K122: 1 | L122: $ | M122: 32338.7 | N122: 0 | O122: 0 | P122: 0 | Q122: 6791.13 | R122: 39129.83
A123: 45968 | B123: 1 | C123: 10 | D123: 12250 | E123: =TEXT(C123,"0000")&TEXT(D123,"00000000") -> 001000012250 | F123: =I123&E123 -> 30502036269001000012250 | G123: 75459973629420 | H123: 80 | I123: 30502036269 | J123: BURGERT SA | K123: 1 | L123: $ | M123: 1058387.6 | N123: 0 | O123: 0 | P123: 0 | Q123: 222261.38 | R123: 1280648.9
A124: 45968 | B124: 1 | C124: 3 | D124: 2394 | E124: =TEXT(C124,"0000")&TEXT(D124,"00000000") -> 000300002394 | F124: =I124&E124 -> 30612003919000300002394 | G124: 75459917314006 | H124: 80 | I124: 30612003919 | J124: COOPERATIVA DE OBRAS Y SERVICIOS PUBLICOS DE DEVOTO LTDA. | K124: 1 | L124: $ | M124: 14876.03 | N124: 0 | O124: 0 | P124: 0 | Q124: 3123.97 | R124: 18000
A125: 45968 | B125: 1 | C125: 10 | D125: 12251 | E125: =TEXT(C125,"0000")&TEXT(D125,"00000000") -> 001000012251 | F125: =I125&E125 -> 30502036269001000012251 | G125: 75459973867042 | H125: 80 | I125: 30502036269 | J125: BURGERT SA | K125: 1 | L125: $ | M125: 2393304.8 | N125: 0 | O125: 0 | P125: 0 | Q125: 502594.01 | R125: 2895898.8
A126: 45968 | B126: 1 | C126: 8 | D126: 2011 | E126: =TEXT(C126,"0000")&TEXT(D126,"00000000") -> 000800002011 | F126: =I126&E126 -> 30684420085000800002011 | G126: 75455908567413 | H126: 80 | I126: 30684420085 | J126: TECMEC SUDAMERICA SA | K126: 1 | L126: $ | M126: 2389500 | N126: 0 | O126: 0 | P126: 0 | Q126: 501795 | R126: 2891295
A127: 45968 | B127: 1 | C127: 3 | D127: 1084 | E127: =TEXT(C127,"0000")&TEXT(D127,"00000000") -> 000300001084 | F127: =I127&E127 -> 30717522636000300001084 | G127: 75456942751847 | H127: 80 | I127: 30717522636 | J127: CURCIO NEGOCIOS INMOBILIARIOS S. R. L. | K127: 1 | L127: $ | M127: 918250.51 | N127: 57846.88 | O127: 0 | P127: 0 | Q127: 192832.61 | R127: 1168930
A128: 45968 | B128: 1 | C128: 27 | D128: 29623 | E128: =TEXT(C128,"0000")&TEXT(D128,"00000000") -> 002700029623 | F128: =I128&E128 -> 33708336969002700029623 | G128: 75459958946526 | H128: 80 | I128: 33708336969 | J128: ESPERANZA COMBUSTIBLES S.A | K128: 1 | L128: $ | M128: 804945.49 | N128: 0 | O128: 0 | P128: 132873.95 | Q128: 169038.55 | R128: 1106858
A129: 45968 | B129: 1 | C129: 3950 | D129: 5354505 | E129: =TEXT(C129,"0000")&TEXT(D129,"00000000") -> 395005354505 | F129: =I129&E129 -> 30639453738395005354505 | G129: 75458073082713 | H129: 80 | I129: 30639453738 | J129: TELECOM ARGENTINA SOCIEDAD ANONIMA | K129: 1 | L129: $ | M129: 6053.72 | N129: 0 | O129: 0 | P129: 181.61 | Q129: 1271.28 | R129: 7506.61
... A149: 45971 | B149: 1 | C149: 2 | D149: 7212 | E149: =TEXT(C149,"0000")&TEXT(D149,"00000000") -> 000200007212 | F149: =I149&E149 -> 27217310291000200007212 | G149: 75461593238794 | H149: 80 | I149: 27217310291 | J149: STON NORMA BEATRIZ | K149: 1 | L149: $ | M149: 42900 | N149: 0 | O149: 0 | P149: 0 | Q149: 9009 | R149: 51909
A150: 45971 | B150: 1 | C150: 32 | D150: 254431 | E150: =TEXT(C150,"0000")&TEXT(D150,"00000000") -> 003200254431 | F150: =I150&E150 -> 30621181838003200254431 | G150: 75458346605337 | H150: 80 | I150: 30621181838 | J150: DISAL S A | K150: 1 | L150: $ | M150: 48686207 | P150: 608577.59 | Q150: 10224104 | R150: 59518888
A151: 45971 | B151: 1 | C151: 267 | D151: 906884 | E151: =TEXT(C151,"0000")&TEXT(D151,"00000000") -> 026700906884 | F151: =I151&E151 -> 30500529454026700906884 | G151: 75454479998210 | H151: 80 | I151: 30500529454 | J151: AKZO NOBEL ARGENTINA S.A | K151: 1 | L151: $ | M151: 46503264 | N151: 0 | O151: 0 | P151: 2557679.5 | Q151: 9765685.5 | R151: 58826629
A152: 45971 | B152: 1 | C152: 215 | D152: 100483 | E152: =TEXT(C152,"0000")&TEXT(D152,"00000000") -> 021500100483 | F152: =I152&E152 -> 30500529071021500100483 | G152: 35431670074949 | H152: 80 | I152: 30500529071 | J152: SAINT-GOBAIN ARGENTINA SA | K152: 1 | L152: $ | M152: 408227.67 | P152: 22452.52 | Q152: 85727.81 | R152: 516408.01
A153: 45971 | B153: 3 | C153: 32 | D153: 165238 | E153: =TEXT(C153,"0000")&TEXT(D153,"00000000") -> 003200165238 | F153: =I153&E153 -> 30621181838003200165238 | G153: 75458346604852 | H153: 80 | I153: 30621181838 | J153: DISAL S A | K153: 1 | L153: $ | M153: 38220762 | P153: 0 | Q153: 8026360 | R153: 46247122
A154: 45971 | B154: 3 | C154: 32 | D154: 165239 | E154: =TEXT(C154,"0000")&TEXT(D154,"00000000") -> 003200165239 | F154: =I154&E154 -> 30621181838003200165239 | G154: 75458346637171 | H154: 80 | I154: 30621181838 | J154: DISAL S A | K154: 1 | L154: $ | M154: 18710842 | P154: 0 | Q154: 3929276.9 | R154: 22640119
A155: 45971 | B155: 3 | C155: 201 | D155: 270207 | E155: =TEXT(C155,"0000")&TEXT(D155,"00000000") -> 020100270207 | F155: =I155&E155 -> 30500529071020100270207 | G155: 35431670074949 | H155: 80 | I155: 30500529071 | J155: SAINT-GOBAIN ARGENTINA SA | K155: 1 | L155: $ | M155: 20411.38 | P155: 612.34 | Q155: 4286.39 | R155: 25310.11
A156: 45971 | B156: 11 | C156: 2 | D156: 532 | E156: =TEXT(C156,"0000")&TEXT(D156,"00000000") -> 000200000532 | F156: =I156&E156 -> 20264502919000200000532 | G156: 75459357482134 | H156: 80 | I156: 20264502919 | J156: SOSA ARNALDO ANDRES | K156: 1 | L156: $ | M156: 0 | N156: 0 | O156: 0 | P156: 0 | Q156: 0 | R156: 3500
A157: 45971 | B157: 11 | C157: 1 | D157: 393 | E157: =TEXT(C157,"0000")&TEXT(D157,"00000000") -> 000100000393 | F157: =I157&E157 -> 20373299791000100000393 | G157: 75451329902405 | H157: 80 | I157: 20373299791 | J157: PORTMANN LEANDRO | K157: 1 | L157: $ | M157: 0 | N157: 0 | O157: 0 | P157: 0 | Q157: 0 | R157: 156250
A158: 45971 | B158: 11 | C158: 4 | D158: 1052 | E158: =TEXT(C158,"0000")&TEXT(D158,"00000000") -> 000400001052 | F158: =I158&E158 -> 20342251464000400001052 | G158: 75454314111395 | H158: 80 | I158: 20342251464 | J158: BALDI DI CINTIO AGUSTIN MARCELO | K158: 1 | L158: $ | M158: 0 | N158: 0 | O158: 0 | P158: 0 | Q158: 0 | R158: 69400
A159: 45972 | B159: 1 | C159: 7 | D159: 1812 | E159: =TEXT(C159,"0000")&TEXT(D159,"00000000") -> 000700001812 | F159: =I159&E159 -> 30715476270000700001812 | G159: 75450480745047 | H159: 80 | I159: 30715476270 | J159: HUGO BAUTISTA BALBI SOCIEDAD ANONIMA | K159: 1 | L159: $ | M159: 8429.75 | N159: 0 | O159: 0 | P159: 0 | Q159: 1770.24 | R159: 10199.99
A160: 45972 | B160: 1 | C160: 2 | D160: 18788 | E160: =TEXT(C160,"0000")&TEXT(D160,"00000000") -> 000200018788 | F160: =I160&E160 -> 30714379468000200018788 | G160: 75458419312401 | H160: 80 | I160: 30714379468 | J160: PAINT & DETAIL S.R.L. | K160: 1 | L160: $ | M160: 1529535.1 | N160: 0 | O160: 0 | P160: 0 | Q160: 321202.37 | R160: 1850737.5
A161: 45972 | B161: 1 | C161: 3 | D161: 1053 | E161: =TEXT(C161,"0000")&TEXT(D161,"00000000") -> 000300001053 | F161: =I161&E161 -> 30718373332000300001053 | G161: 75452460398828 | H161: 80 | I161: 30718373332 | J161: PROINAR MATERIALES S. R. L. | K161: 1 | L161: $ | M161: 90842.98 | N161: 0 | O161: 0 | P161: 0 | Q161: 19077.03 | R161: 109920.01
A162: 45972 | B162: 1 | C162: 5 | D162: 3753 | E162: =TEXT(C162,"0000")&TEXT(D162,"00000000") -> 000500003753 | F162: =I162&E162 -> 23222803039000500003753 | G162: 75459463687756 | H162: 80 | I162: 23222803039 | J162: BERNARDI GUILLERMO LUIS | K162: 1 | L162: $ | M162: 132775.12 | N162: 0 | O162: 0 | P162: 0 | Q162: 27882.78 | R162: 160657.9
...

Sheet Comparativo
A1: CODIGO | B1: DENOMINACION | C1: TD | D1: Nº DOCUMENTO | E1: IVA | F1: FECHA | G1: ESP | H1: SERIE | I1: NUMERO | J1: % IVA | K1: TOTAL | L1: GRAVADO | M1: EXEN/NO GRAV | N1: IVA | O1: IVA Percep | P1: IIBB Percep | Q1: OTROS | R1: EXCL.NET.GRAV | S1: Unido | T1: AFIP IVA | U1: Cmparacion IVA | V1: AFIP Total | W1: Cmparacion Total
A2: 000967 | B2: ZEOCAR SACI | C2: 80 | D2: 30562597464 | E2: I | F2: 22/09/2025 | G2: NCP | H2: A1 | I2: 000400025904 | J2: 21 | K2: -459949.14 | L2: -380123.26 | M2: 0 | N2: -79825.88 | O2: 0 | P2: 0 | Q2: 0 | R2: 0 | S2: 30562597464000400025904 | T2: NO | U2: NO | V2: NO | W2: NO
A3: 000015 | B3: ESCALERAS SIN FIN SOCIEDAD DE HECHO | C3: 80 | D3: 33620532229 | E3: I | F3: 01/10/2025 | G3: NCP | H3: A1 | I3: 000200007977 | J3: 21 | K3: -206388.15 | L3: -170568.72 | M3: 0 | N3: -35819.43 | O3: 0 | P3: 0 | Q3: 0 | R3: 0 | S3: 33620532229000200007977 | T3: NO | U3: NO | V3: NO | W3: NO
A4: 000001 | B4: AKZO NOBEL S.A. - (ALBA & CETOL) | C4: 80 | D4: 30500529454 | E4: I | F4: 03/10/2025 | G4: NCP | H4: A1 | I4: 026700171598 | J4: 21 | K4: -207657.9 | L4: -97841.1 | M4: 0 | N4: -20546.64 | O4: -2935.23 | P4: -2446.03 | Q4: -83888.9 | R4: 0 | S4: 30500529454026700171598 | T4: NO | U4: NO | V4: NO | W4: NO
A5: 000015 | B5: ESCALERAS SIN FIN SOCIEDAD DE HECHO | C5: 80 | D5: 33620532229 | E5: I | F5: 07/10/2025 | G5: NCP | H5: A1 | I5: 000200007985 | J5: 21 | K5: -1506196 | L5: -1244790.1 | M5: 0 | N5: -261405.92 | O5: 0 | P5: 0 | Q5: 0 | R5: 0 | S5: 33620532229000200007985 | T5: NO | U5: NO | V5: NO | W5: NO
A6: 000300 | B6: A A ABRASIVOS ARGENTINOS S.A.I.C. | C6: 80 | D6: 30501044551 | E6: I | F6: 08/10/2025 | G6: NCP | H6: A1 | I6: 000700219976 | J6: 21 | K6: -126936.9 | L6: -30431.38 | M6: 0 | N6: -6390.59 | O6: -912.94 | P6: -760.78 | Q6: -88441.21 | R6: 0 | S6: 30501044551000700219976 | T6: NO | U6: NO | V6: NO | W6: NO
A7: 000001 | B7: AKZO NOBEL S.A. - (ALBA & CETOL) | C7: 80 | D7: 30500529454 | E7: I | F7: 16/10/2025 | G7: NCP | H7: A1 | I7: 026700171749 | J7: 21 | K7: -75705.97 | L7: -62566.92 | M7: 0 | N7: -13139.05 | O7: 0 | P7: 0 | Q7: 0 | R7: 0 | S7: 30500529454026700171749 | T7: NO | U7: NO | V7: NO | W7: NO
A8: 000039 | B8: PREPAN S.A | C8: 80 | D8: 33522734549 | E8: I | F8: 23/10/2025 | G8: NCP | H8: A1 | I8: 002100242470 | J8: 21 | K8: -1668181.7 | L8: -1345307.8 | M8: 0 | N8: -282514.64 | O8: -40359.23 | P8: 0 | Q8: 0 | R8: 0 | S8: 33522734549002100242470 | T8: NO | U8: NO | V8: NO | W8: NO
A9: 000039 | B9: PREPAN S.A | C9: 80 | D9: 33522734549 | E9: I | F9: 23/10/2025 | G9: NCP | H9: A1 | I9: 002100242471 | J9: 21 | K9: -2276867.9 | L9: -1836183.8 | M9: 0 | N9: -385598.6 | O9: -55085.51 | P9: 0 | Q9: 0 | R9: 0 | S9: 33522734549002100242471 | T9: NO | U9: NO | V9: NO | W9: NO
A10: 000039 | B10: PREPAN S.A | C10: 80 | D10: 33522734549 | E10: I | F10: 23/10/2025 | G10: NCP | H10: A1 | I10: 002100242472 | J10: 21 | K10: -5106.02 | L10: -4117.76 | M10: 0 | N10: -864.73 | O10: -123.53 | P10: 0 | Q10: 0 | R10: 0 | S10: 33522734549002100242472 | T10: NO | U10: NO | V10: NO | W10: NO
A11: 000039 | B11: PREPAN S.A | C11: 80 | D11: 33522734549 | E11: I | F11: 23/10/2025 | G11: NCP | H11: A1 | I11: 002100242473 | J11: 21 | K11: -26593.75 | L11: -21446.57 | M11: 0 | N11: -4503.78 | O11: -643.4 | P11: 0 | Q11: 0 | R11: 0 | S11: 33522734549002100242473 | T11: NO | U11: NO | V11: NO | W11: NO
A12: 000039 | B12: PREPAN S.A | C12: 80 | D12: 33522734549 | E12: I | F12: 23/10/2025 | G12: NCP | H12: A1 | I12: 002100242474 | J12: 21 | K12: -383572.04 | L12: -309332.29 | M12: 0 | N12: -64959.78 | O12: -9279.97 | P12: 0 | Q12: 0 | R12: 0 | S12: 33522734549002100242474 | T12: NO | U12: NO | V12: NO | W12: NO
A13: 000102 | B13: FAIP S.A.I.C | C13: 80 | D13: 30523412236 | E13: I | F13: 24/10/2025 | G13: NCP | H13: A1 | I13: 001400012737 | J13: 21 | K13: -1089740 | L13: -900611.59 | M13: 0 | N13: -189128.43 | O13: 0 | P13: 0 | Q13: 0 | R13: 0 | S13: 30523412236001400012737 | T13: NO | U13: NO | V13: NO | W13: NO
... A226: Z9999O | B226: GROSS SERGIO FABIAN | C226: 80 | D226: 23179973219 | E226: M | F226: 30/11/2025 | G226: NF | H226: C | I226: 000200001053 | J226: 0 | K226: 72000 | L226: 0 | M226: 72000 | N226: 0 | O226: 0 | P226: 0 | Q226: 0 | R226: 0 | S226: 23179973219000200001053 | T226: NO | U226: NO | V226: NO | W226: NO
